wikidata2df/__init__.py
wikidata2df/cli.py
wikidata2df/wikidata2df.py
wikidata2df-0.1.0.dist-info/AUTHORS.rst
wikidata2df-0.1.0.dist-info/LICENSE
wikidata2df-0.1.0.dist-info/METADATA
wikidata2df-0.1.0.dist-info/WHEEL
wikidata2df-0.1.0.dist-info/entry_points.txt
wikidata2df-0.1.0.dist-info/top_level.txt
wikidata2df-0.1.0.dist-info/RECORD
