Metadata-Version: 1.2
Name: wikidata2df
Version: 0.1.0
Summary: Utility package for easily turning a SPARQL query into a dataframe
Home-page: https://github.com/jvfe/wikidata2df
Author: João Vitor F. Cavalcante
Author-email: jvfe@ufrn.edu.br
License: BSD license
Keywords: wikidata2df wikidata open-data open data utility
Platform: UNKNOWN
Classifier: Development Status :: 2 - Pre-Alpha
Classifier: Intended Audience :: Developers
Classifier: License :: OSI Approved :: BSD License
Classifier: Natural Language :: English
Classifier: Programming Language :: Python :: 3
Classifier: Programming Language :: Python :: 3.6
Classifier: Programming Language :: Python :: 3.7
Classifier: Programming Language :: Python :: 3.8
Requires-Python: >=3.6
